ears/core/__init__.py
ears/core/client.py
ears/core/events.py
ears/core/exceptions.py
ears/core/handlers.py
ears/core/messaging.py
ears/core/models.py
ears/core/provider.py
ears/core/py.typed
ears/core/transport.py
ears/core/types.py
ears_core-0.1.0a5.dist-info/METADATA
ears_core-0.1.0a5.dist-info/WHEEL
ears_core-0.1.0a5.dist-info/RECORD
